<annotation>
	<folder>新建文件夹 (2)</folder>
	<filename>093508107-015495-015495_1.JPG</filename>
	<path>F:\龟裂\新建文件夹 (2)\093508107-015495-015495_1.JPG</path>
	<source>
		<database>Unknown</database>
	</source>
	<size>
		<width>2048</width>
		<height>2048</height>
		<depth>1</depth>
	</size>
	<segmented>0</segmented>
	<object>
		<name>transverse</name>
		<pose>Unspecified</pose>
		<truncated>0</truncated>
		<difficult>0</difficult>
		<bndbox>
			<xmin>44</xmin>
			<ymin>884</ymin>
			<xmax>2005</xmax>
			<ymax>1221</ymax>
		</bndbox>
	</object>
</annotation>
