<?xml version="1.0" ?>
<annotation>
<folder>longitudinal</folder>
<filename>35638.jpg</filename>
<path>F:\裂缝检测\8\检测车\沥青路面\普通噪声背景\longitudinal\35638.jpg</path>
<source>
    <database>Unknown</database>
</source>
<size>
    <width>1280</width>
    <height>960</height>
    <depth>3</depth>
</size>

<segmented>0</segmented>
    <object>
    <name>longitudinal</name>
    <pose>Unspecified</pose>
    <truncated>0</truncated>
    <difficult>0</difficult>
    <bndbox>
        <xmin>278</xmin>
        <ymin>23</ymin>
        <xmax>347</xmax>
        <ymax>948</ymax>
    </bndbox>
</object>
</annotation>
